autogluon/bench/Dockerfile
autogluon/bench/__init__.py
autogluon/bench/entrypoint.sh
autogluon/bench/main.py
autogluon/bench/runbenchmark.py
autogluon/bench/version.py
autogluon/bench/cloud/__init__.py
autogluon/bench/cloud/aws/__init__.py
autogluon/bench/cloud/aws/app.py
autogluon/bench/cloud/aws/default_config.yaml
autogluon/bench/cloud/aws/deploy.sh
autogluon/bench/cloud/aws/destroy.sh
autogluon/bench/cloud/aws/stack_handler.py
autogluon/bench/cloud/aws/batch_stack/__init__.py
autogluon/bench/cloud/aws/batch_stack/stack.py
autogluon/bench/cloud/aws/batch_stack/constructs/__init__.py
autogluon/bench/cloud/aws/batch_stack/constructs/batch_lambda_function.py
autogluon/bench/cloud/aws/batch_stack/lambdas/__init__.py
autogluon/bench/cloud/aws/batch_stack/lambdas/lambda_function.py
autogluon/bench/cloud/aws/batch_stack/lambdas/requirements.txt
autogluon/bench/cloud/aws/batch_stack/lambdas/custom_configs/amlb_configs/__init__.py
autogluon/bench/custom_configs/amlb_configs/__init__.py
autogluon/bench/custom_configs/dataloaders/__init__.py
autogluon/bench/custom_configs/metrics/__init__.py
autogluon/bench/custom_configs/resources/__init__.py
autogluon/bench/datasets/__init__.py
autogluon/bench/datasets/constants.py
autogluon/bench/datasets/dataset_registry.py
autogluon/bench/datasets/multimodal_dataset.py
autogluon/bench/datasets/object_detection_dataset.py
autogluon/bench/datasets/registry.py
autogluon/bench/eval/__init__.py
autogluon/bench/eval/aggregate/__init__.py
autogluon/bench/eval/aggregate/results.py
autogluon/bench/eval/benchmark_context/__init__.py
autogluon/bench/eval/benchmark_context/output_context.py
autogluon/bench/eval/benchmark_context/output_suite_context.py
autogluon/bench/eval/benchmark_context/utils.py
autogluon/bench/eval/evaluation/__init__.py
autogluon/bench/eval/evaluation/benchmark_evaluator.py
autogluon/bench/eval/evaluation/constants.py
autogluon/bench/eval/evaluation/evaluate_results.py
autogluon/bench/eval/evaluation/evaluate_utils.py
autogluon_bench-0.5.2.dist-info/licenses/LICENSE
autogluon_bench-0.5.2.dist-info/METADATA
autogluon_bench-0.5.2.dist-info/WHEEL
autogluon_bench-0.5.2.dist-info/entry_points.txt
autogluon_bench-0.5.2.dist-info/top_level.txt
autogluon_bench-0.5.2.dist-info/RECORD
