Metadata-Version: 2.4
Name: autogluon.bench
Version: 0.5.2
Summary: A benchmarking tool for AutoML
Author: AutoGluon Community
License:                                  Apache License
Project-URL: Homepage, https://github.com/autogluon/autogluon-bench
Project-URL: Bug Reports, https://github.com/autogluon/autogluon-bench/issues
Classifier: Development Status :: 4 - Beta
Classifier: Intended Audience :: Education
Classifier: Intended Audience :: Developers
Classifier: Intended Audience :: Science/Research
Classifier: Intended Audience :: Customer Service
Classifier: Intended Audience :: Financial and Insurance Industry
Classifier: Intended Audience :: Healthcare Industry
Classifier: Intended Audience :: Telecommunications Industry
Classifier: License :: OSI Approved :: Apache Software License
Classifier: Operating System :: MacOS
Classifier: Operating System :: Microsoft :: Windows
Classifier: Operating System :: POSIX
Classifier: Operating System :: Unix
Classifier: Programming Language :: Python :: 3
Classifier: Programming Language :: Python :: 3.9
Classifier: Programming Language :: Python :: 3.10
Classifier: Programming Language :: Python :: 3.11
Classifier: Programming Language :: Python :: 3.12
Classifier: Topic :: Software Development
Classifier: Topic :: Scientific/Engineering :: Artificial Intelligence
Classifier: Topic :: Scientific/Engineering :: Information Analysis
Classifier: Topic :: Scientific/Engineering :: Image Recognition
Requires-Python: <3.13,>=3.9
License-File: LICENSE
Requires-Dist: autogluon.common<2,>=1
Requires-Dist: aws-cdk-lib<2.205,>=2.0.0
Requires-Dist: awscliv2<2.4,>=2.2
Requires-Dist: boto3<2,>=1.26.0
Requires-Dist: constructs<10.5,>=10.0.0
Requires-Dist: matplotlib<3.11,>=3.4
Requires-Dist: pandas<3,>=2.0.0
Requires-Dist: pyarrow<21,>=19.0.0
Requires-Dist: pyyaml<7,>=5.4
Requires-Dist: ray[default]<3,>=2.6.3
Requires-Dist: tqdm<=5,>=4.64.0
Requires-Dist: typer<1.0.0,>=0.9.0
Requires-Dist: wheel<0.46,>0.38.0
Provides-Extra: tests
Requires-Dist: pytest; extra == "tests"
Requires-Dist: pytest-mock; extra == "tests"
Requires-Dist: tox; extra == "tests"
Requires-Dist: black<=25.1.0,>=23.1.9; extra == "tests"
Requires-Dist: isort<=6.1.0,>=5.11.0; extra == "tests"
Dynamic: license-file
